{"TextDetections": [{"DetectedText": "第四单元", "Confidence": 99, "Polygon": [{"X": 1159, "Y": 76}, {"X": 1159, "Y": 399}, {"X": 1083, "Y": 399}, {"X": 1083, "Y": 76}], "AdvancedInfo": "{\"Parag\":{\"ParagNo\":2}}", "ItemPolygon": {"X": 1159, "Y": 76, "Width": 323, "Height": 76}, "Words": [], "WordCoordPoint": []}, {"DetectedText": "看，花儿在悄悄绽放。听，蜜蜂", "Confidence": 100, "Polygon": [{"X": 242, "Y": 278}, {"X": 855, "Y": 278}, {"X": 855, "Y": 326}, {"X": 242, "Y": 326}], "AdvancedInfo": "{\"Parag\":{\"ParagNo\":1}}", "ItemPolygon": {"X": 242, "Y": 278, "Width": 613, "Height": 48}, "Words": [], "WordCoordPoint": []}, {"DetectedText": "在窃窃私语...", "Confidence": 100, "Polygon": [{"X": 153, "Y": 356}, {"X": 417, "Y": 356}, {"X": 417, "Y": 401}, {"X": 153, "Y": 401}], "AdvancedInfo": "{\"Parag\":{\"ParagNo\":1}}", "ItemPolygon": {"X": 153, "Y": 356, "Width": 264, "Height": 45}, "Words": [], "WordCoordPoint": []}, {"DetectedText": "..自然界如此奇妙，留", "Confidence": 100, "Polygon": [{"X": 415, "Y": 353}, {"X": 855, "Y": 356}, {"X": 854, "Y": 403}, {"X": 415, "Y": 400}], "AdvancedInfo": "{\"Parag\":{\"ParagNo\":1}}", "ItemPolygon": {"X": 415, "Y": 353, "Width": 440, "Height": 47}, "Words": [], "WordCoordPoint": []}, {"DetectedText": "心观察，会有新的发现。", "Confidence": 100, "Polygon": [{"X": 153, "Y": 433}, {"X": 613, "Y": 433}, {"X": 613, "Y": 480}, {"X": 153, "Y": 480}], "AdvancedInfo": "{\"Parag\":{\"ParagNo\":1}}", "ItemPolygon": {"X": 153, "Y": 433, "Width": 460, "Height": 47}, "Words": [], "WordCoordPoint": []}, {"DetectedText": "借助关键语句概括一段话的大意。", "Confidence": 100, "Polygon": [{"X": 590, "Y": 871}, {"X": 1085, "Y": 871}, {"X": 1085, "Y": 911}, {"X": 590, "Y": 911}], "AdvancedInfo": "{\"Parag\":{\"ParagNo\":3}}", "ItemPolygon": {"X": 590, "Y": 871, "Width": 495, "Height": 40}, "Words": [], "WordCoordPoint": []}, {"DetectedText": "观察事物的变化，把实验过程写清楚。", "Confidence": 100, "Polygon": [{"X": 592, "Y": 931}, {"X": 1153, "Y": 931}, {"X": 1153, "Y": 970}, {"X": 592, "Y": 970}], "AdvancedInfo": "{\"Parag\":{\"ParagNo\":4}}", "ItemPolygon": {"X": 592, "Y": 931, "Width": 561, "Height": 39}, "Words": [], "WordCoordPoint": []}, {"DetectedText": " ", "Confidence": 0, "Polygon": [{"X": 1153, "Y": 1607}, {"X": 1153, "Y": 1619}, {"X": 1139, "Y": 1619}, {"X": 1139, "Y": 1607}], "AdvancedInfo": "{\"Parag\":{\"ParagNo\":5}}", "ItemPolygon": {"X": 1153, "Y": 1607, "Width": 12, "Height": 14}, "Words": [], "WordCoordPoint": []}], "Language": "zh", "Angel": 359.989990234375, "PdfPageSize": 0, "Angle": 359.989990234375, "RequestId": "ebebd1b0-81aa-4293-a943-1e818737447d"}