{"TextDetections": [{"DetectedText": "宇宙的另一边", "Confidence": 100, "Polygon": [{"X": 707, "Y": 82}, {"X": 1018, "Y": 82}, {"X": 1018, "Y": 139}, {"X": 707, "Y": 139}], "AdvancedInfo": "{\"Parag\":{\"ParagNo\":1}}", "ItemPolygon": {"X": 707, "Y": 82, "Width": 311, "Height": 57}, "Words": [], "WordCoordPoint": []}, {"DetectedText": "pa", "Confidence": 100, "Polygon": [{"X": 231, "Y": 691}, {"X": 258, "Y": 691}, {"X": 258, "Y": 713}, {"X": 231, "Y": 713}], "AdvancedInfo": "{\"Parag\":{\"ParagNo\":2}}", "ItemPolygon": {"X": 231, "Y": 691, "Width": 27, "Height": 22}, "Words": [], "WordCoordPoint": []}, {"DetectedText": "hao han", "Confidence": 100, "Polygon": [{"X": 536, "Y": 685}, {"X": 619, "Y": 685}, {"X": 619, "Y": 711}, {"X": 536, "Y": 711}], "AdvancedInfo": "{\"Parag\":{\"ParagNo\":3}}", "ItemPolygon": {"X": 536, "Y": 685, "Width": 83, "Height": 26}, "Words": [], "WordCoordPoint": []}, {"DetectedText": "我趴在窗台上，看着浩瀚的星空。", "Confidence": 100, "Polygon": [{"X": 187, "Y": 709}, {"X": 750, "Y": 709}, {"X": 750, "Y": 754}, {"X": 187, "Y": 754}], "AdvancedInfo": "{\"Parag\":{\"ParagNo\":4}}", "ItemPolygon": {"X": 187, "Y": 709, "Width": 563, "Height": 45}, "Words": [], "WordCoordPoint": []}, {"DetectedText": "giu", "Confidence": 100, "Polygon": [{"X": 747, "Y": 764}, {"X": 775, "Y": 758}, {"X": 779, "Y": 779}, {"X": 751, "Y": 785}], "AdvancedInfo": "{\"Parag\":{\"ParagNo\":5}}", "ItemPolygon": {"X": 747, "Y": 764, "Width": 28, "Height": 21}, "Words": [], "WordCoordPoint": []}, {"DetectedText": "tang", "Confidence": 100, "Polygon": [{"X": 863, "Y": 756}, {"X": 911, "Y": 756}, {"X": 911, "Y": 782}, {"X": 863, "Y": 782}], "AdvancedInfo": "{\"Parag\":{\"ParagNo\":6}}", "ItemPolygon": {"X": 863, "Y": 756, "Width": 48, "Height": 26}, "Words": [], "WordCoordPoint": []}, {"DetectedText": "星光洒进我的眼睛，在我身体里汩汩流淌，", "Confidence": 100, "Polygon": [{"X": 191, "Y": 780}, {"X": 927, "Y": 780}, {"X": 927, "Y": 822}, {"X": 191, "Y": 822}], "AdvancedInfo": "{\"Parag\":{\"ParagNo\":7}}", "ItemPolygon": {"X": 191, "Y": 780, "Width": 736, "Height": 42}, "Words": [], "WordCoordPoint": []}, {"DetectedText": "告诉我一", "Confidence": 100, "Polygon": [{"X": 925, "Y": 780}, {"X": 1103, "Y": 780}, {"X": 1103, "Y": 822}, {"X": 925, "Y": 822}], "AdvancedInfo": "{\"Parag\":{\"ParagNo\":7}}", "ItemPolygon": {"X": 925, "Y": 780, "Width": 178, "Height": 42}, "Words": [], "WordCoordPoint": []}, {"DetectedText": "mi", "Confidence": 100, "Polygon": [{"X": 159, "Y": 830}, {"X": 179, "Y": 830}, {"X": 179, "Y": 845}, {"X": 159, "Y": 845}], "AdvancedInfo": "{\"Parag\":{\"ParagNo\":7}}", "ItemPolygon": {"X": 159, "Y": 830, "Width": 20, "Height": 15}, "Words": [], "WordCoordPoint": []}, {"DetectedText": "个秘密:很远很远的地方，宇宙的另一边，是这一边的倒", "Confidence": 100, "Polygon": [{"X": 110, "Y": 847}, {"X": 1103, "Y": 847}, {"X": 1103, "Y": 891}, {"X": 110, "Y": 891}], "AdvancedInfo": "{\"Parag\":{\"ParagNo\":8}}", "ItemPolygon": {"X": 110, "Y": 847, "Width": 993, "Height": 44}, "Words": [], "WordCoordPoint": []}, {"DetectedText": "dong", "Confidence": 100, "Polygon": [{"X": 1064, "Y": 883}, {"X": 1115, "Y": 893}, {"X": 1109, "Y": 924}, {"X": 1058, "Y": 914}], "AdvancedInfo": "{\"Parag\":{\"ParagNo\":8}}", "ItemPolygon": {"X": 1064, "Y": 883, "Width": 51, "Height": 31}, "Words": [], "WordCoordPoint": []}, {"DetectedText": "影。那里有座一样的城市，有条一样的街道，街角处有栋", "Confidence": 100, "Polygon": [{"X": 110, "Y": 915}, {"X": 1107, "Y": 915}, {"X": 1107, "Y": 960}, {"X": 110, "Y": 960}], "AdvancedInfo": "{\"Parag\":{\"ParagNo\":8}}", "ItemPolygon": {"X": 110, "Y": 915, "Width": 997, "Height": 45}, "Words": [], "WordCoordPoint": []}, {"DetectedText": "一样的房子，房子里有个一样的孩子。", "Confidence": 100, "Polygon": [{"X": 112, "Y": 982}, {"X": 752, "Y": 982}, {"X": 752, "Y": 1028}, {"X": 112, "Y": 1028}], "AdvancedInfo": "{\"Parag\":{\"ParagNo\":8}}", "ItemPolygon": {"X": 112, "Y": 982, "Width": 640, "Height": 46}, "Words": [], "WordCoordPoint": []}, {"DetectedText": "那个孩子是另一个我吗?当我从书包里拿出作业本的", "Confidence": 100, "Polygon": [{"X": 189, "Y": 1052}, {"X": 1103, "Y": 1052}, {"X": 1103, "Y": 1095}, {"X": 189, "Y": 1095}], "AdvancedInfo": "{\"Parag\":{\"ParagNo\":9}}", "ItemPolygon": {"X": 189, "Y": 1052, "Width": 914, "Height": 43}, "Words": [], "WordCoordPoint": []}, {"DetectedText": "x0", "Confidence": 100, "Polygon": [{"X": 955, "Y": 1101}, {"X": 978, "Y": 1101}, {"X": 978, "Y": 1121}, {"X": 955, "Y": 1121}], "AdvancedInfo": "{\"Parag\":{\"ParagNo\":10}}", "ItemPolygon": {"X": 955, "Y": 1101, "Width": 23, "Height": 20}, "Words": [], "WordCoordPoint": []}, {"DetectedText": "时候，他是不是正把作业本放回书包?当我气喘吁吁爬楼", "Confidence": 100, "Polygon": [{"X": 110, "Y": 1121}, {"X": 1105, "Y": 1121}, {"X": 1105, "Y": 1163}, {"X": 110, "Y": 1163}], "AdvancedInfo": "{\"Parag\":{\"ParagNo\":11}}", "ItemPolygon": {"X": 110, "Y": 1121, "Width": 995, "Height": 42}, "Words": [], "WordCoordPoint": []}, {"DetectedText": "梯的时候，他是不是正下楼去?当我趴在窗台看着星空的", "Confidence": 100, "Polygon": [{"X": 108, "Y": 1189}, {"X": 1103, "Y": 1189}, {"X": 1103, "Y": 1232}, {"X": 108, "Y": 1232}], "AdvancedInfo": "{\"Parag\":{\"ParagNo\":11}}", "ItemPolygon": {"X": 108, "Y": 1189, "Width": 995, "Height": 43}, "Words": [], "WordCoordPoint": []}, {"DetectedText": "时候，他会不会也趴在窗台，看着星空，想着我呢?我们", "Confidence": 100, "Polygon": [{"X": 110, "Y": 1258}, {"X": 1105, "Y": 1258}, {"X": 1105, "Y": 1300}, {"X": 110, "Y": 1300}], "AdvancedInfo": "{\"Parag\":{\"ParagNo\":11}}", "ItemPolygon": {"X": 110, "Y": 1258, "Width": 995, "Height": 42}, "Words": [], "WordCoordPoint": []}, {"DetectedText": "的目光会在哪里相遇?", "Confidence": 100, "Polygon": [{"X": 110, "Y": 1329}, {"X": 477, "Y": 1329}, {"X": 477, "Y": 1369}, {"X": 110, "Y": 1369}], "AdvancedInfo": "{\"Parag\":{\"ParagNo\":11}}", "ItemPolygon": {"X": 110, "Y": 1329, "Width": 367, "Height": 40}, "Words": [], "WordCoordPoint": []}, {"DetectedText": "在宇宙的这一边，雪是在冬天下的;那么，在宇宙的", "Confidence": 100, "Polygon": [{"X": 187, "Y": 1395}, {"X": 1103, "Y": 1395}, {"X": 1103, "Y": 1440}, {"X": 187, "Y": 1440}], "AdvancedInfo": "{\"Parag\":{\"ParagNo\":12}}", "ItemPolygon": {"X": 187, "Y": 1395, "Width": 916, "Height": 45}, "Words": [], "WordCoordPoint": []}, {"DetectedText": "本文作者陈诗哥，选作课文时有改动。", "Confidence": 100, "Polygon": [{"X": 110, "Y": 1502}, {"X": 530, "Y": 1502}, {"X": 530, "Y": 1532}, {"X": 110, "Y": 1532}], "AdvancedInfo": "{\"Parag\":{\"ParagNo\":13}}", "ItemPolygon": {"X": 110, "Y": 1502, "Width": 420, "Height": 30}, "Words": [], "WordCoordPoint": []}, {"DetectedText": "60", "Confidence": 100, "Polygon": [{"X": 108, "Y": 1603}, {"X": 143, "Y": 1603}, {"X": 143, "Y": 1631}, {"X": 108, "Y": 1631}], "AdvancedInfo": "{\"Parag\":{\"ParagNo\":14}}", "ItemPolygon": {"X": 108, "Y": 1603, "Width": 35, "Height": 28}, "Words": [], "WordCoordPoint": []}], "Language": "zh", "Angel": 359.989990234375, "PdfPageSize": 0, "Angle": 359.989990234375, "RequestId": "7edf4957-affb-4d15-bf9f-5bb644fb664f"}